{
  "type": "forge:ore_shaped",
  "pattern": [
    "ILI",
    "GEG",
    "IRI"
  ],
  "key": {
    "I": {
      "type": "forge:ore_dict",
      "ore": "ingotIron"
    },
    "L": {
      "type": "forge:ore_dict",
      "ore": "blockLapis"
    },
    "E": {
      "type": "forge:ore_dict",
      "ore": "enderpearl"
    },
    "R": {
      "type": "forge:ore_dict",
      "ore": "blockRedstone"
    },
    "G": {
      "type": "forge:ore_dict",
      "ore": "dustGlowstone"
    }
  },
  "result": {
    "item": "wormhole:portal_stabilizer"
  }
}